<?xml version="1.0" encoding="utf-8" ?>
<dwsync>
<file name="addPost.asp" server="ftp.bitn.com.br/web/" local="132624327952417559" remote="132602367000000000" Dst="0" />
<file name="regua.asp" server="ftp.bitn.com.br/web/" local="132624327952417559" remote="132601992000000000" Dst="0" />
<file name="lateral2.asp" server="ftp.bitn.com.br/web/" local="132624327953546155" remote="132602024400000000" Dst="0" />
<file name="lateral.asp" server="ftp.bitn.com.br/web/" local="132624327953625435" remote="132602286000000000" Dst="0" />
<file name="inc_user.asp" server="ftp.bitn.com.br/web/" local="132624327953725161" remote="132598386000000000" Dst="0" />
<file name="menu.asp" server="ftp.bitn.com.br/web/" local="132624327955131317" remote="132582936000000000" Dst="0" />
<file name="rodape.asp" server="ftp.bitn.com.br/web/" local="132624327955131317" remote="132603548400000000" Dst="0" />
<file name="editPost.asp" server="ftp.bitn.com.br/web/" local="132624327956053864" remote="132602361000000000" Dst="0" />
<file name="topo.asp" server="ftp.bitn.com.br/web/" local="132624327956752142" remote="132603576600000000" Dst="0" />
</dwsync>